Metadata-Version: 2.1
Name: upheaval-proto
Version: 0.0.0
Summary: Protos for Upheaval Chain protocol
Home-page: UNKNOWN
Author: Upheaval Protocol
Author-email: contact@upheaval.fi
License: UNKNOWN
Platform: UNKNOWN
Requires-Python: >=3.8
